streamsx/testing/__init__.py
streamsx/testing/_fn.py
streamsx/testing/nose.py
streamsx.testing-0.3.1.dist-info/LICENSE.txt
streamsx.testing-0.3.1.dist-info/METADATA
streamsx.testing-0.3.1.dist-info/RECORD
streamsx.testing-0.3.1.dist-info/WHEEL
streamsx.testing-0.3.1.dist-info/entry_points.txt
streamsx.testing-0.3.1.dist-info/top_level.txt
